servicex_local/__init__.py
servicex_local/adaptor.py
servicex_local/codegen.py
servicex_local/create_x509.py
servicex_local/deliver.py
servicex_local/logging_decorator.py
servicex_local/science_images.py
servicex_local/version.txt
servicex_local/templates/transform_single_file.sh
servicex_local/templates/transformer_capabilities_xaod.json
servicex_local-1.0.0b7.dist-info/METADATA
servicex_local-1.0.0b7.dist-info/WHEEL
servicex_local-1.0.0b7.dist-info/entry_points.txt
servicex_local-1.0.0b7.dist-info/RECORD
