Metadata-Version: 2.4
Name: servicex-local
Version: 1.0.0b7
Summary: Enables a local backend for ServiceX
Project-URL: Homepage, https://github.com/gordonwatts/ServiceX-Local
Project-URL: Issue Tracker, https://github.com/gordonwatts/ServiceX-Local/issues
Project-URL: Release Notes, https://github.com/gordonwatts/ServiceX-Local/releases
Project-URL: Releases, https://github.com/gordonwatts/ServiceX-Local/releases
Project-URL: Source Code, https://github.com/gordonwatts/ServiceX-Local
Author-email: Gordon Watts <gwatts@uw.edu>
License: BSD-3-Clause
Classifier: Development Status :: 4 - Beta
Classifier: Intended Audience :: Science/Research
Classifier: License :: OSI Approved :: BSD License
Classifier: Operating System :: OS Independent
Classifier: Programming Language :: Python :: 3
Classifier: Programming Language :: Python :: 3 :: Only
Classifier: Programming Language :: Python :: 3.9
Classifier: Programming Language :: Python :: 3.10
Classifier: Programming Language :: Python :: 3.11
Classifier: Programming Language :: Python :: 3.12
Classifier: Programming Language :: Python :: 3.13
Classifier: Programming Language :: Python :: Implementation :: CPython
Classifier: Topic :: Scientific/Engineering
Classifier: Topic :: Scientific/Engineering :: Physics
Requires-Python: >=3.9
Requires-Dist: click
Requires-Dist: make-it-sync
Requires-Dist: requests-toolbelt
Requires-Dist: servicex>=3.0.0
Requires-Dist: tenacity
Provides-Extra: develop
Requires-Dist: servicex[docs,test,xaod]; extra == 'develop'
Provides-Extra: docs
Requires-Dist: autodoc-pydantic==2.2.0; extra == 'docs'
Requires-Dist: furo>=2023.5.20; extra == 'docs'
Requires-Dist: myst-parser>=3.0.1; extra == 'docs'
Requires-Dist: sphinx-code-include>=1.4.0; extra == 'docs'
Requires-Dist: sphinx-copybutton>=0.5.2; extra == 'docs'
Requires-Dist: sphinx-tabs>=3.4.5; extra == 'docs'
Requires-Dist: sphinx>=7.0.1; extra == 'docs'
Provides-Extra: test
Requires-Dist: black; extra == 'test'
Requires-Dist: flake8>=5.0.4; extra == 'test'
Requires-Dist: func-adl-xaod; extra == 'test'
Requires-Dist: pytest-asyncio>=0.21.0; extra == 'test'
Requires-Dist: pytest-console-scripts>=1.4.1; extra == 'test'
Requires-Dist: pytest-cov>=4.0.0; extra == 'test'
Requires-Dist: pytest-mock>=3.10.0; extra == 'test'
Requires-Dist: pytest>=7.2.0; extra == 'test'
Provides-Extra: xaod
Requires-Dist: func-adl-xaod; extra == 'xaod'
